flor/__init__.py
flor/__main__.py
flor/api.py
flor/cli.py
flor/clock.py
flor/constants.py
flor/database.py
flor/obj_store.py
flor/orm.py
flor/repl.py
flor/utils.py
flor/versions.py
flor/hlast/__init__.py
flor/hlast/gtpropagate.py
flor/hlast/visitors.py
flor/hlast/gumtree/__init__.py
flor/hlast/gumtree/adapter.py
flor/hlast/gumtree/idmap.py
flor/hlast/gumtree/priorityq.py
flor/hlast/gumtree/python.py
flor/hlast/gumtree/test.py
flor/hlast/gumtree/tree.py
florflow-3.3.3.dist-info/LICENSE
florflow-3.3.3.dist-info/METADATA
florflow-3.3.3.dist-info/WHEEL
florflow-3.3.3.dist-info/top_level.txt
florflow-3.3.3.dist-info/RECORD
